gotcha/__init___.py
gotcha/__main__.py
gotcha/__version__.py
gotcha/ascii.py
gotcha/gotcha_tty.py
ttyGotcha-1.0.1.dist-info/LICENSE
ttyGotcha-1.0.1.dist-info/METADATA
ttyGotcha-1.0.1.dist-info/WHEEL
ttyGotcha-1.0.1.dist-info/entry_points.txt
ttyGotcha-1.0.1.dist-info/top_level.txt
ttyGotcha-1.0.1.dist-info/RECORD
