Metadata-Version: 2.1
Name: ttyGotcha
Version: 1.0.1
Summary: SSH-TTY control Interface
Home-page: https://github.com/caputomarcos/gotcha
Author: Marcos Caputo
Author-email: caputo.marcos@gmail.com
License: MIT
Keywords: hunter,security
Classifier: Environment :: Console
Classifier: License :: OSI Approved :: MIT License
Classifier: Natural Language :: English
Classifier: Operating System :: OS Independent
Classifier: Programming Language :: Python :: 3.10
Classifier: Programming Language :: Python :: 3 :: Only
Classifier: Topic :: Security
Requires-Python: >=3.10.7
License-File: LICENSE
Requires-Dist: altgraph (==0.17.3)
Requires-Dist: bleach (==5.0.1)
Requires-Dist: certifi (==2022.9.24)
Requires-Dist: cffi (==1.15.1)
Requires-Dist: charset-normalizer (==2.1.1)
Requires-Dist: commonmark (==0.9.1)
Requires-Dist: cryptography (==38.0.1)
Requires-Dist: dataclasses (==0.6)
Requires-Dist: docutils (==0.19)
Requires-Dist: future (==0.18.2)
Requires-Dist: idna (==3.4)
Requires-Dist: importlib-metadata (==5.0.0)
Requires-Dist: jaraco.classes (==3.2.3)
Requires-Dist: jeepney (==0.8.0)
Requires-Dist: keyring (==23.9.3)
Requires-Dist: more-itertools (==8.14.0)
Requires-Dist: packaging (==21.3)
Requires-Dist: pkginfo (==1.8.3)
Requires-Dist: psutil (==5.9.2)
Requires-Dist: pycparser (==2.21)
Requires-Dist: pyelftools (==0.29)
Requires-Dist: Pygments (==2.13.0)
Requires-Dist: pyinstaller (==5.5)
Requires-Dist: pyinstaller-hooks-contrib (==2022.10)
Requires-Dist: pyparsing (==3.0.8)
Requires-Dist: readme-renderer (==37.2)
Requires-Dist: requests (==2.28.1)
Requires-Dist: requests-toolbelt (==0.10.0)
Requires-Dist: rfc3986 (==2.0.0)
Requires-Dist: rich (==12.6.0)
Requires-Dist: SecretStorage (==3.3.3)
Requires-Dist: six (==1.16.0)
Requires-Dist: staticx (==0.13.8)
Requires-Dist: twine (==4.0.1)
Requires-Dist: urllib3 (==1.26.12)
Requires-Dist: webencodings (==0.5.1)
Requires-Dist: zipp (==3.9.0)
